python_text_utils/__init__.py
python_text_utils/generic.py
python_text_utils/greek.py
python_text_utils/tests/__init__.py
python_text_utils/tests/test_generic.py
python_text_utils/tests/test_greek.py
python_text_utils-0.0.6.dist-info/DESCRIPTION.rst
python_text_utils-0.0.6.dist-info/METADATA
python_text_utils-0.0.6.dist-info/RECORD
python_text_utils-0.0.6.dist-info/WHEEL
python_text_utils-0.0.6.dist-info/metadata.json
python_text_utils-0.0.6.dist-info/top_level.txt
